COPYING
MANIFEST.in
README.md
README.txt
setup.py
src/jottacloudclientmonitor.py
src/jottacloudclientscanner.py
src/jottacloudclient/__init__.py
src/jottacloudclient/jottacloud.py
src/jottacloudclient.egg-info/PKG-INFO
src/jottacloudclient.egg-info/SOURCES.txt
src/jottacloudclient.egg-info/dependency_links.txt
src/jottacloudclient.egg-info/requires.txt
src/jottacloudclient.egg-info/top_level.txt