Metadata-Version: 1.0
Name: jottacloudclient
Version: 0.2.5-1
Summary: A cli friendly sync client for JottaCloud
Home-page: https://gitorious.org/jottafs/jottacloudclient.git
Author: Håvard Gulldahl
Author-email: havard@gulldahl.no
License: GPLv3
Platform: UNKNOWN
